cff/VERSION
cff/__init__.py
cff/origin_request.py
cff/py.typed
cff/models/__init__.py
cff/models/cloudfront_event.py
cff/models/header.py
cff/models/lambda_event.py
cff/models/py.typed
cff/models/record.py
cff/models/request.py
cff/models/response.py
cff/models/response_headers.py
cff-1.0.0a1.dist-info/LICENSE
cff-1.0.0a1.dist-info/METADATA
cff-1.0.0a1.dist-info/WHEEL
cff-1.0.0a1.dist-info/top_level.txt
cff-1.0.0a1.dist-info/RECORD
