Metadata-Version: 2.1
Name: cff
Version: 1.0.0a1
Summary: Amazon Web Services CloudFront lambda function bootstraps
Home-page: https://github.com/cariad/cff
Author: Cariad Eccleston
Author-email: cariad@cariad.earth
License: MIT
Platform: UNKNOWN
Classifier: Development Status :: 3 - Alpha
Classifier: Environment :: Other Environment
Classifier: License :: OSI Approved :: MIT License
Classifier: Natural Language :: English
Classifier: Operating System :: OS Independent
Classifier: Programming Language :: Python :: 3.9
Classifier: Topic :: Internet :: WWW/HTTP
Classifier: Typing :: Typed
Requires-Python: >=3.9
